nta/__about__.py
nta/__init__.py
nta/api.py
nta/exceptions.py
nta/utils.py
nta/models/__init__.py
nta/models/base.py
nta/models/buttons.py
nta/models/events.py
nta/models/payload.py
nta/models/responses.py
nta/models/template.py
nta-1.0.6.dist-info/LICENSE.txt
nta-1.0.6.dist-info/METADATA
nta-1.0.6.dist-info/WHEEL
nta-1.0.6.dist-info/top_level.txt
nta-1.0.6.dist-info/RECORD
