Metadata-Version: 2.1
Name: nta
Version: 1.0.6
Summary: A Python Library For Naver TalkTalk
Home-page: https://github.com/hwonyo/naver_talk_sdk
Author: wonyoHwang
Author-email: hollal0726@gmail.com
License: MIT License
Keywords: nta,navertalk,naver,chatbot
Classifier: Development Status :: 3 - Alpha
Classifier: Intended Audience :: Developers
Classifier: Programming Language :: Python
Classifier: Programming Language :: Python :: 3
Classifier: License :: OSI Approved :: MIT License
License-File: LICENSE.txt
Requires-Dist: requests >=2.20.0
